cvxreg/__init__.py
cvxreg/base.py
cvxreg/constant.py
cvxreg/datasets/__init__.py
cvxreg/datasets/_base.py
cvxreg/datasets/data/41Firm.csv
cvxreg/datasets/data/Boston.csv
cvxreg/datasets/data/__init__.py
cvxreg/datasets/data/electricityFirms.csv
cvxreg/models/__init__.py
cvxreg/models/_base.py
cvxreg/models/_cqr.py
cvxreg/models/_cvxpy_opt.py
cvxreg/models/_penalized.py
cvxreg/utils/__init__.py
cvxreg/utils/_param_check.py
cvxreg/utils/check.py
cvxreg/utils/extmath.py
cvxreg-0.2.2.dist-info/licenses/LICENSE
cvxreg-0.2.2.dist-info/METADATA
cvxreg-0.2.2.dist-info/WHEEL
cvxreg-0.2.2.dist-info/top_level.txt
cvxreg-0.2.2.dist-info/RECORD
