Metadata-Version: 2.4
Name: cvxreg
Version: 0.2.2
Summary: A Python Package for Convex Regression
Home-page: https://github.com/ConvexRegression/cvxreg
Download-URL: https://pypi.org/project/cvxreg/
Author: Zhiqiang Liao
Author-email: zhiqiang.liao@aalto.fi
License: MIT
Keywords: ML,Prediction,Regression
Classifier: Development Status :: 5 - Production/Stable
Classifier: Intended Audience :: Science/Research
Classifier: Programming Language :: Python :: 3
Classifier: License :: OSI Approved :: MIT License
Classifier: Operating System :: OS Independent
Requires-Python: >=3.7
License-File: LICENSE
Requires-Dist: numpy>=1.19.2
Requires-Dist: pandas>=1.1.3
Requires-Dist: scipy>=1.5.2
Requires-Dist: cvxpy>=1.1.7
Requires-Dist: scikit-learn>=0.23.2
Dynamic: author
Dynamic: author-email
Dynamic: classifier
Dynamic: description
Dynamic: description-content-type
Dynamic: download-url
Dynamic: home-page
Dynamic: keywords
Dynamic: license
Dynamic: license-file
Dynamic: requires-dist
Dynamic: requires-python
Dynamic: summary
